varex.py
varex-0.1.dist-info/LICENSE
varex-0.1.dist-info/METADATA
varex-0.1.dist-info/WHEEL
varex-0.1.dist-info/top_level.txt
varex-0.1.dist-info/RECORD
